nonebot_plugin_dialectlist/__init__.py
nonebot_plugin_dialectlist/config.py
nonebot_plugin_dialectlist/schema.py
nonebot_plugin_dialectlist/time.py
nonebot_plugin_dialectlist/usage.py
nonebot_plugin_dialectlist/utils.py
nonebot_plugin_dialectlist/template/rank_template.j2
nonebot_plugin_dialectlist/template/avatar/default.jpg
nonebot_plugin_dialectlist/template/css/style.css
nonebot_plugin_dialectlist-3.0.1.dist-info/licenses/LICENSE
nonebot_plugin_dialectlist-3.0.1.dist-info/METADATA
nonebot_plugin_dialectlist-3.0.1.dist-info/WHEEL
nonebot_plugin_dialectlist-3.0.1.dist-info/top_level.txt
nonebot_plugin_dialectlist-3.0.1.dist-info/RECORD
