Metadata-Version: 2.4
Name: nonebot-plugin-dialectlist
Version: 3.0.1
Summary: 看看你群群友有多能说
Author-email: Chen_Xu233 <woyerpa@outlook.com>
License: MIT
Requires-Python: <4.0,>=3.9
License-File: LICENSE
Requires-Dist: nonebot-plugin-chatrecorder>=0.7.0
Requires-Dist: nonebot-plugin-orm[default]
Requires-Dist: nonebot-plugin-apscheduler>=0.4.0
Requires-Dist: nonebot-plugin-alconna>=0.50.2
Requires-Dist: nonebot-plugin-cesaa>=0.4.0
Requires-Dist: nonebot-plugin-userinfo>=0.2.6
Requires-Dist: nonebot-plugin-htmlrender>=0.3.3
Requires-Dist: nonebot2>=2.3.2
Requires-Dist: pillow>=11.3.0
Requires-Dist: nonebot-plugin-uninfo>=0.1.1
Provides-Extra: dev
Requires-Dist: ruff>=0.5.5; extra == "dev"
Requires-Dist: setuptools>=80.9.0; extra == "dev"
Requires-Dist: twine>=6.2.0; extra == "dev"
Requires-Dist: nb-cli>=1.4.2; extra == "dev"
Requires-Dist: py-spy>=0.3.14; extra == "dev"
Provides-Extra: test
Requires-Dist: nonebot-adapter-onebot>=2.4.4; extra == "test"
Dynamic: license-file
